[
  ["BXG-09","S H","DrDg 2-80 GP",{"coat":"black"}],
  ["BX-33","B","WsTg 3-60 U"],
  ["UX-05","RB","ShSh 1-80 MN","RSo7irNan4Q"],["UX-05","RB H","ShSh 9-60 LF"],["UX-05","RB H","ShSh 3-70 GP"],
  ["BXG-08","B H","HlCh 5-60 HT",{"coat":"black"}],
  ["BXG-04","B","DRS 4-80 P","ko--Stv3vBk"],
  ["BX-31","RB","TyBt 4-70 Q","N4uCIB8AyJ4"],["BX-31","RB H","TyBt 3-60 S"],["BX-31","RB H","HlCh 9-80 O"],
  ["BX-31","RB H","DrDg 4-70 P"],["BX-31","RB H","ShEd 1-60 Q"],["BX-31","RB H","RhHr 5-80 Q"],
  ["UX-04","SS H","DrBs 1-60 A","MnqRC7QtBnQ"],["UX-04","SS H","WzRd 5-70 DB"],
  ["UX-03","B","WzRd 5-70 DB","503x_5cbm5Y"],["UX-02","S","HlHm 3-70 H","503x_5cbm5Y"],["UX-01","S","DrBs 1-60 A","503x_5cbm5Y"],
  ["BXG-06","B H","ShEd 5-60 GF",{"coat":"dodgerblue"}],["BXG-05","B H","LnCl 5-60 P",{"coat":"gold"}],
  ["BX-27","RB","SpCw 9-80 GN","viKnigAkOmk"],["BX-27","RB H","SpCw 4-80 HT"],["BX-27","RB H","SpCw 5-60 O"],
  ["BX-26","B","UnSt 5-60 GP","znFmcS08Ls4"],
  ["BX-24","RB","WyGl 5-80 GB","4OZ-UxlaX1E"],["BX-24","RB H","WyGl 3-60 T"],["BX-24","RB H","KnLn 4-60 GB"],
  ["BX-24","RB H","VpTl 5-60 F"],["BX-24","RB H","LnCl 3-80 HN"],["BX-24","RB H","WzAr 4-80 GB"],
  ["BX-23","S","PhWn 9-60 GF","AJ0IfMWiTm0",{"coat":"red"}],["BH","hidden","PhFt"],["BX-22","S H","DrSw 3-60 F","pbKqZsWXSdE"],
  ["BX-21","St","HlCh 5-60 HT","oC_ZrfuqQK0"],["BX-21","St H","KnLn 3-60 LF"],["BX-21","St H","WzAr 4-80 N"],
  ["BX-20","St","DrDg 4-60 R","oC_ZrfuqQK0"],["BX-20","St H","ShEd 3-80 F"],["BX-20","St H","KnSh 5-80 T"],
  ["BX-19","B","RhHr 3-80 S","BQuGU3VQmik"],
  ["BX-17","SS H","DrSw 3-60 F","iLhqV8xDz3A"],["BX-17","SS H","WzAr 4-80 B"],
  ["BX-16","RB","VpTl 5-80 O","Zd7a84oIOqI"],["BX-16","RB H","VpTl 4-60 F"],["BX-16","RB H","VpTl 3-80 HN"],
  ["BX-15","S","LnCl 5-60 P","ThESmPNYhmM"],["BXG-03","B H","HlSc 4-60 T",{"coat":"gold"}],
  ["BX-14","RB","ShEd 3-60 LF","9ITlNCP0ERQ"],["BX-14","RB H","ShEd 4-80 N"],["BX-14","RB H","DrSw 3-80 B"],
  ["BX-14","RB H","HlSc 4-80 LF"],["BX-14","RB H","KnSh 4-60 LF"],["BX-14","RB H","WzAr 3-60 T"],
  ["BH","hidden","CbDr"],
  ["BX-13","B","KnLn 4-80 HN","Nd4fev66JwU"],
  ["BXG-01","B","DZS 3-80 T","Zu7WiN6gr7g"],
  ["BX-08","St H","KnSh 4-80 T","tM8ILMmozhk"],["BX-08","St H","WzAr 4-60 N"],["BX-08","St H","HlSc 3-80 B"],
  ["BX-07","SS H","DrSw 3-60 F","qSai0ksbPss"],
  ["BX-06","B H","KnSh 3-80 N","Zc2tfhrXxBA"],["BX-05","B H","WzAr 4-80 B","Zc2tfhrXxBA"],
  ["BX-04","S","KnSh 3-80 N","ztd9tpZs6dA"],["BX-03","S","WzAr 4-80 B","ztd9tpZs6dA"],
  ["BX-02","S","HlSc 4-60 T","ztd9tpZs6dA"],["BX-01","S","DrSw 3-60 F","ztd9tpZs6dA"]
]
